rtl/alu.v
module alu #(parameter WIDTH = 8)
(
    input clk,
    input rst,

    input en,
    input lp_mode,

    input [WIDTH-1:0] A,
    input [WIDTH-1:0] B,

    input [3:0] opcode,

    output reg [WIDTH-1:0] result,

    output reg zero,
    output reg carry,
    output reg overflow,
    output reg negative
);

reg [WIDTH:0] temp;

wire [WIDTH-1:0] A_iso;
wire [WIDTH-1:0] B_iso;

// Operand Isolation
assign A_iso = (en) ? A : {WIDTH{1'b0}};
assign B_iso = (en) ? B : {WIDTH{1'b0}};

always @(posedge clk or posedge rst)
begin

    if(rst)
    begin
        result <= 0;
        zero <= 0;
        carry <= 0;
        overflow <= 0;
        negative <= 0;
    end

    else if(en)
    begin

        carry <= 0;
        overflow <= 0;

        case(opcode)

        // ADD
        4'b0000:
        begin
            temp = A_iso + B_iso;
            result <= temp[WIDTH-1:0];
            carry <= temp[WIDTH];
        end

        // SUB
        4'b0001:
        begin
            temp = A_iso - B_iso;
            result <= temp[WIDTH-1:0];
            carry <= temp[WIDTH];
        end

        // AND
        4'b0010:
            result <= A_iso & B_iso;

        // OR
        4'b0011:
            result <= A_iso | B_iso;

        // XOR
        4'b0100:
            result <= A_iso ^ B_iso;

        // NOT A
        4'b0101:
            result <= ~A_iso;

        // Shift Left
        4'b0110:
            result <= A_iso << 1;

        // Shift Right
        4'b0111:
            result <= A_iso >> 1;

        // Increment
        4'b1000:
            result <= A_iso + 1;

        // Decrement
        4'b1001:
            result <= A_iso - 1;

        // Compare
        4'b1010:
        begin
            if(A_iso > B_iso)
                result <= 8'd1;
            else if(A_iso == B_iso)
                result <= 8'd0;
            else
                result <= 8'd255;
        end

        default:
            result <= 0;

        endcase

        zero <= (result == 0);
        negative <= result[WIDTH-1];

    end

end

endmodule

tb/alu_tb.v
`timescale 1ns/1ps

module alu_tb;

reg clk;
reg rst;

reg en;
reg lp_mode;

reg [7:0] A;
reg [7:0] B;

reg [3:0] opcode;

wire [7:0] result;

wire zero;
wire carry;
wire overflow;
wire negative;

alu DUT(
.clk(clk),
.rst(rst),
.en(en),
.lp_mode(lp_mode),
.A(A),
.B(B),
.opcode(opcode),
.result(result),
.zero(zero),
.carry(carry),
.overflow(overflow),
.negative(negative)
);

always #5 clk = ~clk;

initial
begin

    $dumpfile("waves.vcd");
    $dumpvars(0,alu_tb);

    clk = 0;
    rst = 1;

    en = 0;
    lp_mode = 0;

    A = 0;
    B = 0;
    opcode = 0;

    #20;
    rst = 0;
    en = 1;

    // ADD
    A = 20;
    B = 10;
    opcode = 4'b0000;
    #20;

    // SUB
    A = 30;
    B = 10;
    opcode = 4'b0001;
    #20;

    // AND
    A = 8'hF0;
    B = 8'h0F;
    opcode = 4'b0010;
    #20;

    // OR
    opcode = 4'b0011;
    #20;

    // XOR
    opcode = 4'b0100;
    #20;

    // NOT
    opcode = 4'b0101;
    #20;

    // Shift Left
    opcode = 4'b0110;
    #20;

    // Shift Right
    opcode = 4'b0111;
    #20;

    // Increment
    opcode = 4'b1000;
    #20;

    // Decrement
    opcode = 4'b1001;
    #20;

    // Compare
    A = 50;
    B = 20;
    opcode = 4'b1010;
    #20;

    // Low Power Mode
    lp_mode = 1;
    en = 0;
    #40;

    $finish;

end

initial
begin

$monitor(
"Time=%0t A=%d B=%d OPC=%b Result=%d Z=%b C=%b N=%b",
$time,
A,
B,
opcode,
result,
zero,
carry,
negative
);

end

endmodule

waves.vcd
$date
	Mon Jun 22 21:00:26 2026
$end
$version
	Icarus Verilog
$end
$timescale
	1ps
$end
$scope module alu_tb $end
$var wire 1 ! zero $end
$var wire 8 " result [7:0] $end
$var wire 1 # overflow $end
$var wire 1 $ negative $end
$var wire 1 % carry $end
$var reg 8 & A [7:0] $end
$var reg 8 ' B [7:0] $end
$var reg 1 ( clk $end
$var reg 1 ) en $end
$var reg 1 * lp_mode $end
$var reg 4 + opcode [3:0] $end
$var reg 1 , rst $end
$scope module DUT $end
$var wire 8 - A [7:0] $end
$var wire 8 . B [7:0] $end
$var wire 1 ( clk $end
$var wire 1 ) en $end
$var wire 1 * lp_mode $end
$var wire 4 / opcode [3:0] $end
$var wire 1 , rst $end
$var wire 8 0 B_iso [7:0] $end
$var wire 8 1 A_iso [7:0] $end
$var parameter 32 2 WIDTH $end
$var reg 1 % carry $end
$var reg 1 $ negative $end
$var reg 1 # overflow $end
$var reg 8 3 result [7:0] $end
$var reg 9 4 temp [8:0] $end
$var reg 1 ! zero $end
$upscope $end
$upscope $end
$enddefinitions $end
$comment Show the parameter values. $end
$dumpall
b1000 2
$end
#0
$dumpvars
bx 4
b0 3
b0 1
b0 0
b0 /
b0 .
b0 -
1,
b0 +
0*
0)
0(
b0 '
b0 &
0%
0$
0#
b0 "
0!
$end
#5000
1(
#10000
0(
#15000
1(
#20000
b10100 1
b1010 0
0(
b1010 '
b1010 .
b10100 &
b10100 -
1)
0,
#25000
1!
b11110 "
b11110 3
b11110 4
1(
#30000
0(
#35000
0!
1(
#40000
b11110 1
0(
b1 +
b1 /
b11110 &
b11110 -
#45000
b10100 "
b10100 3
b10100 4
1(
#50000
0(
#55000
1(
#60000
b1111 0
b11110000 1
0(
b10 +
b10 /
b1111 '
b1111 .
b11110000 &
b11110000 -
#65000
b0 "
b0 3
1(
#70000
0(
#75000
1!
1(
#80000
0(
b11 +
b11 /
#85000
b11111111 "
b11111111 3
1(
#90000
0(
#95000
1$
0!
1(
#100000
0(
b100 +
b100 /
#105000
1(
#110000
0(
#115000
1(
#120000
0(
b101 +
b101 /
#125000
b1111 "
b1111 3
1(
#130000
0(
#135000
0$
1(
#140000
0(
b110 +
b110 /
#145000
b11100000 "
b11100000 3
1(
#150000
0(
#155000
1$
1(
#160000
0(
b111 +
b111 /
#165000
b1111000 "
b1111000 3
1(
#170000
0(
#175000
0$
1(
#180000
0(
b1000 +
b1000 /
#185000
b11110001 "
b11110001 3
1(
#190000
0(
#195000
1$
1(
#200000
0(
b1001 +
b1001 /
#205000
b11101111 "
b11101111 3
1(
#210000
0(
#215000
1(
#220000
b10100 0
b110010 1
0(
b1010 +
b1010 /
b10100 '
b10100 .
b110010 &
b110010 -
#225000
b1 "
b1 3
1(
#230000
0(
#235000
0$
1(
#240000
b0 1
b0 0
0(
0)
1*
